setup.py
txbonjour/__init__.py
txbonjour/discovery.py
txbonjour/service.py
txbonjour/tap.py
txbonjour.egg-info/PKG-INFO
txbonjour.egg-info/SOURCES.txt
txbonjour.egg-info/dependency_links.txt
txbonjour.egg-info/entry_points.txt
txbonjour.egg-info/not-zip-safe
txbonjour.egg-info/requires.txt
txbonjour.egg-info/top_level.txt