Metadata-Version: 1.0
Name: txbonjour
Version: 0.4
Summary: An easy way to use the bonjour/avahi service with Twisted.
Home-page: https://github.com/jdcumpson/txbonjour
Author: jdcumpson
Author-email: cumpsonjd@gmail.com
License: UNKNOWN
Platform: UNKNOWN
